[
    {
        "title": "ONE day...",
        "text": "... to get it all right",
        "id": "MKCM"
    },
    {
        "title": "TWO wrong...",
        "text": "...and not enough right",
        "id": 777
    },
    {
        "title": "THREE words...",
        "text": "... you said in the night",
        "id": 123
    },
    {
        "title": "Be-FOUR....",
        "text": "... we held the fire",
        "id": "7015"
    },
    {
        "title": "HIGH FIVE me...",
        "text": "... brother it's amazing",
        "id": "d3e4"
    },
    {
        "title": "Her SIX shooter...",
        "text": "... came out blazing",
        "id": "bf5f"
    },
    {
        "title": "SEVEN up and coke...",
        "text": "... on the pavement",
        "id": "25fa"
    },
    {
        "title": "EIGHT my heart out...",
        "text": "... daily",
        "id": "2peq"
    }

]